{"images":[{"image":37264,"name":"Bristol Central Reference Library, BLS FFBJ 2431792","description":"Bristoliensis on goods to boycott eg mahogany, rice, dyes, etc, Felix Farley's Bristol Journal 24 March 1792","copyright":"\u00a9 Bristol Central Reference Library"}],"name":"Boycotting","id":2431,"description":null,"summary":null,"source":null,"keywords":[],"type":["Subtheme"],"location":"","objects":[[]],"child":[{"image":37264,"name":"Boycotting","link":"boycotting","id":3293}],"parent":[{"image":45533,"name":"CHALLENGING","link":"challenging","id":2594}]}